timely_timed/__init__.py
timely_timed-0.3.0.dist-info/licenses/LICENSE
timely_timed-0.3.0.dist-info/METADATA
timely_timed-0.3.0.dist-info/WHEEL
timely_timed-0.3.0.dist-info/top_level.txt
timely_timed-0.3.0.dist-info/RECORD
