Metadata-Version: 2.4
Name: timely-timed
Version: 0.3.0
Summary: A Python package for fetching UTC time from multiple time servers with fallback logic. Features free servers.
Home-page: https://gitlab.com/lorrooar/timely-timed
Author: Mike Berensmeier
Author-email: berensmeier.mike@keemail.me
Keywords: time,utc,datetime,http,api
Classifier: Development Status :: 3 - Alpha
Classifier: Intended Audience :: Developers
Classifier: License :: OSI Approved :: MIT License
Classifier: Operating System :: OS Independent
Classifier: Programming Language :: Python :: 3
Classifier: Programming Language :: Python :: 3.8
Classifier: Programming Language :: Python :: 3.9
Classifier: Programming Language :: Python :: 3.10
Classifier: Programming Language :: Python :: 3.11
Classifier: Programming Language :: Python :: 3.12
Classifier: Programming Language :: Python :: 3.13
Classifier: Programming Language :: Python :: 3.14
Requires-Python: >=3.8
License-File: LICENSE
Dynamic: author
Dynamic: author-email
Dynamic: classifier
Dynamic: description
Dynamic: description-content-type
Dynamic: home-page
Dynamic: keywords
Dynamic: license-file
Dynamic: requires-python
Dynamic: summary
